{
  "version": "1.8.15",
  "notes": "听泉Cursor Pool v1.8.15 更新\n- 修复自动更新签名验证问题\n- 优化更新检测机制\n- 提升软件稳定性和用户体验",
  "pub_date": "2025-01-11T12:00:00.000Z",
  "platforms": {
    "darwin-aarch64": {
      "signature": "待更新",
      "url": "https://vip.123pan.cn/1831210026/tq_pool/tingquancursor-pool_aarch64.app.tar.gz"
    },
    "darwin-x86_64": {
      "signature": "待更新",
      "url": "https://vip.123pan.cn/1831210026/tq_pool/tingquancursor-pool_x64.app.tar.gz"
    },
    "windows-x86_64": {
      "signature": "待更新",
      "url": "https://vip.123pan.cn/1831210026/tq_pool/tingquancursor-pool_1.8.15_x64_zh-CN.msi"
    },
    "windows-aarch64": {
      "signature": "待更新",
      "url": "https://vip.123pan.cn/1831210026/tq_pool/tingquancursor-pool_1.8.15_arm64_zh-CN.msi"
    }
  }
} 